{
"annotations": {"list": []},
"editable": true,
"fiscalYearStartMonth": 0,
"graphTooltip": 0,
"id": null,
"links": [],
"liveNow": false,
"panels": [
    {
    "type": "timeseries",
    "title": "Data drift share",
    "gridPos": {"h": 8, "w": 12, "x": 0, "y": 0},
    "id": 1,
    "targets": [
        {
        "expr": "medai_data_drift_share",
        "refId": "A",
        "datasource": {"type": "prometheus", "uid": "prometheus"}
        }
    ],
    "fieldConfig": {
        "defaults": {"min": 0, "max": 1, "unit": "percentunit"}
    },
    "datasource": {"type": "prometheus", "uid": "prometheus"}
    },
    {
    "type": "timeseries",
    "title": "API request rate (per second, 1m window)",
    "gridPos": {"h": 8, "w": 12, "x": 12, "y": 0},
    "id": 2,
    "targets": [
        {
        "expr": "rate(http_requests_total[1m])",
        "refId": "A",
        "datasource": {"type": "prometheus", "uid": "prometheus"}
        }
    ],
    "datasource": {"type": "prometheus", "uid": "prometheus"}
    },
    {
    "type": "stat",
    "title": "Drift detected",
    "gridPos": {"h": 4, "w": 6, "x": 0, "y": 8},
    "id": 3,
    "targets": [
        {
        "expr": "medai_data_drift_detected",
        "refId": "A",
        "datasource": {"type": "prometheus", "uid": "prometheus"}
        }
    ],
    "fieldConfig": {
        "defaults": {
        "mappings": [
            {"type": "value", "options": {"0": {"text": "No", "color": "green"}, "1": {"text": "Yes", "color": "red"}}}
        ]
        }
    },
    "datasource": {"type": "prometheus", "uid": "prometheus"}
    },
    {
    "type": "stat",
    "title": "Drift iterations",
    "gridPos": {"h": 4, "w": 6, "x": 6, "y": 8},
    "id": 4,
    "targets": [
        {
        "expr": "medai_drift_iterations_total",
        "refId": "A",
        "datasource": {"type": "prometheus", "uid": "prometheus"}
        }
    ],
    "datasource": {"type": "prometheus", "uid": "prometheus"}
    }
],
"refresh": "10s",
"schemaVersion": 39,
"tags": ["medai-a1"],
"templating": {"list": []},
"time": {"from": "now-15m", "to": "now"},
"timepicker": {},
"timezone": "",
"title": "medai-a1 overview",
"uid": "medai-a1-overview",
"version": 1,
"weekStart": ""
}